gemini_framework/__init__.py
gemini_framework/abstract/__init__.py
gemini_framework/abstract/database_driver_abstract.py
gemini_framework/abstract/database_reader_abstract.py
gemini_framework/abstract/filter.py
gemini_framework/abstract/unit_abstract.py
gemini_framework/abstract/unit_module_abstract.py
gemini_framework/app.py
gemini_framework/database/__init__.py
gemini_framework/database/connector/__init__.py
gemini_framework/database/connector/avevadb_driver.py
gemini_framework/database/connector/csv_driver.py
gemini_framework/database/connector/influxdb_driver.py
gemini_framework/database/connector/osisoftpi_driver.py
gemini_framework/database/influxdb_aveva_reader_db.py
gemini_framework/database/influxdb_csv_reader_db.py
gemini_framework/database/influxdb_osisoftpi_reader_db.py
gemini_framework/framework/__init__.py
gemini_framework/framework/boot_plant.py
gemini_framework/framework/filter/mean_filter.py
gemini_framework/framework/filter/statuscode.py
gemini_framework/framework/loop.py
gemini_framework/framework/mainmodule.py
gemini_framework/framework/plant.py
gemini_framework/framework/preprocessor.py
gemini_framework/modules/__init__.py
gemini_framework/modules/blowdown/__init__.py
gemini_framework/modules/blowdown/unit.py
gemini_framework/modules/boosterpump/__init__.py
gemini_framework/modules/boosterpump/unit.py
gemini_framework/modules/degasser/__init__.py
gemini_framework/modules/degasser/unit.py
gemini_framework/modules/electricboiler/__init__.py
gemini_framework/modules/electricboiler/unit.py
gemini_framework/modules/esp/__init__.py
gemini_framework/modules/esp/calculate_theoretical_head.py
gemini_framework/modules/esp/calculate_theoretical_outlet_pressure.py
gemini_framework/modules/esp/calculate_theoretical_power.py
gemini_framework/modules/esp/calculate_vlp_head.py
gemini_framework/modules/esp/calculate_vlp_ipr_inlet_pressure.py
gemini_framework/modules/esp/calculate_vlp_outlet_pressure.py
gemini_framework/modules/esp/preprocessor.py
gemini_framework-0.3.2.dist-info/LICENSE
gemini_framework-0.3.2.dist-info/METADATA
gemini_framework-0.3.2.dist-info/WHEEL
gemini_framework-0.3.2.dist-info/RECORD
