Metadata-Version: 2.1
Name: gemini-framework
Version: 0.3.2
Summary: 
Author: Ryvo Octaviano
Author-email: ryvo.octaviano@tno.nl
Requires-Python: >=3.11,<4.0
Classifier: Development Status :: 4 - Beta
Classifier: Intended Audience :: Developers
Classifier: Intended Audience :: Science/Research
Classifier: License :: OSI Approved :: GNU General Public License v3 (GPLv3)
Classifier: Operating System :: OS Independent
Classifier: Programming Language :: Python :: 3
Classifier: Programming Language :: Python :: 3.11
Classifier: Programming Language :: Python :: 3.12
Classifier: Topic :: Scientific/Engineering
Classifier: Topic :: Software Development
Requires-Dist: adh-sample-library-preview (>=0.10.11rc0,<0.11.0)
Requires-Dist: flake8 (>=7.0.0,<8.0.0)
Requires-Dist: flake8-docstrings (>=1.7.0,<2.0.0)
Requires-Dist: gemini-model (==0.3.0)
Requires-Dist: influxdb-client (>=1.43.0,<2.0.0)
Requires-Dist: matplotlib (>=3.9.0,<4.0.0)
Requires-Dist: pytest (>=8.2.2,<9.0.0)
Requires-Dist: pytest-cov (>=5.0.0,<6.0.0)
Requires-Dist: pytz (>=2024.1,<2025.0)
Requires-Dist: requests (>=2.28.0,<3.0.0)
